side_by_side/__init__.py
side_by_side/diff.py
side_by_side-0.0.2.dist-info/METADATA
side_by_side-0.0.2.dist-info/WHEEL
side_by_side-0.0.2.dist-info/top_level.txt
side_by_side-0.0.2.dist-info/RECORD
