Metadata-Version: 2.1
Name: side-by-side
Version: 0.0.2
Summary: Print two files side-by-side (in columns)
Home-page: https://github.com/jxmorris12/side-by-side
Author: Jack Morris
Author-email: jxmorris12@gmail.com
License: MIT
Platform: UNKNOWN
